<?xml version="1.0" encoding="utf-8"?>
<Entity parent="template_unit_champion_cavalry_spearman">
  <Cost>
    <Resources>
      <food>0</food>
      <wood>0</wood>
      <stone>0</stone>
      <metal>300</metal>
    </Resources>
  </Cost>
  <Identity>
    <Civ>west</Civ>
    <SpecificName>Mounted Knight Templar</SpecificName>
    <Icon>units/west_champion_cavalry_spearman_templar.png</Icon>
  </Identity>
  <VisualActor>
    <Actor>units/templar/cavalry_spearman_c_m.xml</Actor>
  </VisualActor>
</Entity>
